<?xml version="1.0" encoding="UTF-8"?>
<analysisEngineDeploymentDescription xmlns="http://uima.apache.org/resourceSpecifier">
  
  <name>Annotation3</name>
  <description>Deploys remotely deployed TestElementAnnotator.</description>
  
  <deployment protocol="jms" provider="activemq">
    <service>
      <inputQueue endpoint="Annotator3RemoteQ" brokerURL="tcp://localhost:61616"/>
      <topDescriptor>
        <import location="analysisEngine.xml"/>
      </topDescriptor>
    </service>
  </deployment>
  
</analysisEngineDeploymentDescription>
